README.md
fake_keepall/__init__.py
fake_keepall-0.1.2.dist-info/entry_points.txt
fake_keepall-0.1.2.dist-info/WHEEL
fake_keepall-0.1.2.dist-info/METADATA
fake_keepall-0.1.2.dist-info/RECORD
